{
  "brand": "DJI",
  "brand_slug": "dji",
  "products": {
    "clmedia-2833": {
      "id": "clmedia-2833",
      "source": "clmedia",
      "source_id": "2833",
      "name": "DJI Lito X1 플라이 모어 콤보 플러스 (RC 2) 리토1 드론 입문용",
      "brand": "DJI",
      "brand_slug": "dji",
      "category": "CameraSupport",
      "cat_path": [
        "CameraSupport"
      ],
      "price": 946000,
      "source_url": "https://www.clmedia.co.kr/product/dji-lito-x1-플라이-모어-콤보-플러스-rc-2-리토1-드론-입문용/2833/category/184/display/1/",
      "images": {
        "thumb": "https://media.nadaun.co/shop/thumbnails/dji/clmedia-2833.webp",
        "main": [
          "https://media.nadaun.co/shop/images/dji/clmedia-2833/main_1.webp",
          "https://media.nadaun.co/shop/images/dji/clmedia-2833/main_2.webp"
        ],
        "detail": [
          "https://media.nadaun.co/shop/detail/dji/clmedia-2833/01.webp",
          "https://media.nadaun.co/shop/detail/dji/clmedia-2833/03.webp",
          "https://media.nadaun.co/shop/detail/dji/clmedia-2833/05.webp",
          "https://media.nadaun.co/shop/detail/dji/clmedia-2833/06.webp",
          "https://media.nadaun.co/shop/detail/dji/clmedia-2833/07.webp",
          "https://media.nadaun.co/shop/detail/dji/clmedia-2833/08.webp",
          "https://media.nadaun.co/shop/detail/dji/clmedia-2833/09.webp",
          "https://media.nadaun.co/shop/detail/dji/clmedia-2833/10.webp",
          "https://media.nadaun.co/shop/detail/dji/clmedia-2833/11.webp",
          "https://media.nadaun.co/shop/detail/dji/clmedia-2833/12.webp",
          "https://media.nadaun.co/shop/detail/dji/clmedia-2833/13.webp",
          "https://media.nadaun.co/shop/detail/dji/clmedia-2833/15.webp",
          "https://media.nadaun.co/shop/detail/dji/clmedia-2833/17.webp",
          "https://media.nadaun.co/shop/detail/dji/clmedia-2833/18.webp"
        ]
      }
    },
    "clmedia-2832": {
      "id": "clmedia-2832",
      "source": "clmedia",
      "source_id": "2832",
      "name": "DJI Lito X1 플라이 모어 콤보 (RC 2) 리토1 드론 입문용",
      "brand": "DJI",
      "brand_slug": "dji",
      "category": "CameraSupport",
      "cat_path": [
        "CameraSupport"
      ],
      "price": 841000,
      "source_url": "https://www.clmedia.co.kr/product/dji-lito-x1-플라이-모어-콤보-rc-2-리토1-드론-입문용/2832/category/184/display/1/",
      "images": {
        "thumb": "https://media.nadaun.co/shop/thumbnails/dji/clmedia-2832.webp",
        "main": [
          "https://media.nadaun.co/shop/images/dji/clmedia-2832/main_1.webp",
          "https://media.nadaun.co/shop/images/dji/clmedia-2832/main_2.webp"
        ],
        "detail": [
          "https://media.nadaun.co/shop/detail/dji/clmedia-2832/01.webp",
          "https://media.nadaun.co/shop/detail/dji/clmedia-2832/03.webp",
          "https://media.nadaun.co/shop/detail/dji/clmedia-2832/05.webp",
          "https://media.nadaun.co/shop/detail/dji/clmedia-2832/06.webp",
          "https://media.nadaun.co/shop/detail/dji/clmedia-2832/07.webp",
          "https://media.nadaun.co/shop/detail/dji/clmedia-2832/08.webp",
          "https://media.nadaun.co/shop/detail/dji/clmedia-2832/09.webp",
          "https://media.nadaun.co/shop/detail/dji/clmedia-2832/10.webp",
          "https://media.nadaun.co/shop/detail/dji/clmedia-2832/11.webp",
          "https://media.nadaun.co/shop/detail/dji/clmedia-2832/12.webp",
          "https://media.nadaun.co/shop/detail/dji/clmedia-2832/13.webp",
          "https://media.nadaun.co/shop/detail/dji/clmedia-2832/15.webp",
          "https://media.nadaun.co/shop/detail/dji/clmedia-2832/17.webp",
          "https://media.nadaun.co/shop/detail/dji/clmedia-2832/18.webp"
        ]
      }
    },
    "clmedia-2831": {
      "id": "clmedia-2831",
      "source": "clmedia",
      "source_id": "2831",
      "name": "DJI Lito X1 플라이 모어 콤보 (RC-N3) 리토1 드론 입문용",
      "brand": "DJI",
      "brand_slug": "dji",
      "category": "CameraSupport",
      "cat_path": [
        "CameraSupport"
      ],
      "price": 714000,
      "source_url": "https://www.clmedia.co.kr/product/dji-lito-x1-플라이-모어-콤보-rc-n3-리토1-드론-입문용/2831/category/184/display/1/",
      "images": {
        "thumb": "https://media.nadaun.co/shop/thumbnails/dji/clmedia-2831.webp",
        "main": [
          "https://media.nadaun.co/shop/images/dji/clmedia-2831/main_1.webp",
          "https://media.nadaun.co/shop/images/dji/clmedia-2831/main_2.webp"
        ],
        "detail": [
          "https://media.nadaun.co/shop/detail/dji/clmedia-2831/01.webp",
          "https://media.nadaun.co/shop/detail/dji/clmedia-2831/03.webp",
          "https://media.nadaun.co/shop/detail/dji/clmedia-2831/05.webp",
          "https://media.nadaun.co/shop/detail/dji/clmedia-2831/06.webp",
          "https://media.nadaun.co/shop/detail/dji/clmedia-2831/07.webp",
          "https://media.nadaun.co/shop/detail/dji/clmedia-2831/08.webp",
          "https://media.nadaun.co/shop/detail/dji/clmedia-2831/09.webp",
          "https://media.nadaun.co/shop/detail/dji/clmedia-2831/10.webp",
          "https://media.nadaun.co/shop/detail/dji/clmedia-2831/11.webp",
          "https://media.nadaun.co/shop/detail/dji/clmedia-2831/12.webp",
          "https://media.nadaun.co/shop/detail/dji/clmedia-2831/13.webp",
          "https://media.nadaun.co/shop/detail/dji/clmedia-2831/15.webp",
          "https://media.nadaun.co/shop/detail/dji/clmedia-2831/17.webp",
          "https://media.nadaun.co/shop/detail/dji/clmedia-2831/18.webp"
        ]
      }
    },
    "clmedia-2828": {
      "id": "clmedia-2828",
      "source": "clmedia",
      "source_id": "2828",
      "name": "DJI Lito X1 단품 (RC-N3) 리토1 드론 입문용",
      "brand": "DJI",
      "brand_slug": "dji",
      "category": "CameraSupport",
      "cat_path": [
        "CameraSupport"
      ],
      "price": 524000,
      "source_url": "https://www.clmedia.co.kr/product/dji-lito-x1-단품-rc-n3-리토1-드론-입문용/2828/category/184/display/1/",
      "images": {
        "thumb": "https://media.nadaun.co/shop/thumbnails/dji/clmedia-2828.webp",
        "main": [
          "https://media.nadaun.co/shop/images/dji/clmedia-2828/main_1.webp",
          "https://media.nadaun.co/shop/images/dji/clmedia-2828/main_2.webp"
        ],
        "detail": [
          "https://media.nadaun.co/shop/detail/dji/clmedia-2828/01.webp",
          "https://media.nadaun.co/shop/detail/dji/clmedia-2828/03.webp",
          "https://media.nadaun.co/shop/detail/dji/clmedia-2828/05.webp",
          "https://media.nadaun.co/shop/detail/dji/clmedia-2828/06.webp",
          "https://media.nadaun.co/shop/detail/dji/clmedia-2828/07.webp",
          "https://media.nadaun.co/shop/detail/dji/clmedia-2828/08.webp",
          "https://media.nadaun.co/shop/detail/dji/clmedia-2828/09.webp",
          "https://media.nadaun.co/shop/detail/dji/clmedia-2828/10.webp",
          "https://media.nadaun.co/shop/detail/dji/clmedia-2828/11.webp",
          "https://media.nadaun.co/shop/detail/dji/clmedia-2828/12.webp",
          "https://media.nadaun.co/shop/detail/dji/clmedia-2828/13.webp",
          "https://media.nadaun.co/shop/detail/dji/clmedia-2828/15.webp",
          "https://media.nadaun.co/shop/detail/dji/clmedia-2828/17.webp",
          "https://media.nadaun.co/shop/detail/dji/clmedia-2828/18.webp"
        ]
      }
    },
    "clmedia-2827": {
      "id": "clmedia-2827",
      "source": "clmedia",
      "source_id": "2827",
      "name": "DJI Lito 1 플라이 모어 콤보 (RC-N3) 리토1 드론 입문용",
      "brand": "DJI",
      "brand_slug": "dji",
      "category": "CameraSupport",
      "cat_path": [
        "CameraSupport"
      ],
      "price": 590000,
      "source_url": "https://www.clmedia.co.kr/product/dji-lito-1-플라이-모어-콤보-rc-n3-리토1-드론-입문용/2827/category/184/display/1/",
      "images": {
        "thumb": "https://media.nadaun.co/shop/thumbnails/dji/clmedia-2827.webp",
        "main": [
          "https://media.nadaun.co/shop/images/dji/clmedia-2827/main_1.webp",
          "https://media.nadaun.co/shop/images/dji/clmedia-2827/main_2.webp"
        ],
        "detail": [
          "https://media.nadaun.co/shop/detail/dji/clmedia-2827/01.webp",
          "https://media.nadaun.co/shop/detail/dji/clmedia-2827/03.webp",
          "https://media.nadaun.co/shop/detail/dji/clmedia-2827/05.webp",
          "https://media.nadaun.co/shop/detail/dji/clmedia-2827/06.webp",
          "https://media.nadaun.co/shop/detail/dji/clmedia-2827/07.webp",
          "https://media.nadaun.co/shop/detail/dji/clmedia-2827/08.webp",
          "https://media.nadaun.co/shop/detail/dji/clmedia-2827/09.webp",
          "https://media.nadaun.co/shop/detail/dji/clmedia-2827/10.webp",
          "https://media.nadaun.co/shop/detail/dji/clmedia-2827/11.webp",
          "https://media.nadaun.co/shop/detail/dji/clmedia-2827/12.webp",
          "https://media.nadaun.co/shop/detail/dji/clmedia-2827/13.webp",
          "https://media.nadaun.co/shop/detail/dji/clmedia-2827/15.webp",
          "https://media.nadaun.co/shop/detail/dji/clmedia-2827/17.webp",
          "https://media.nadaun.co/shop/detail/dji/clmedia-2827/18.webp"
        ]
      }
    },
    "clmedia-2826": {
      "id": "clmedia-2826",
      "source": "clmedia",
      "source_id": "2826",
      "name": "DJI Lito 1 단품 (RC-N3) 리토1 드론 입문용",
      "brand": "DJI",
      "brand_slug": "dji",
      "category": "CameraSupport",
      "cat_path": [
        "CameraSupport"
      ],
      "price": 421000,
      "source_url": "https://www.clmedia.co.kr/product/dji-lito-1-단품-rc-n3-리토1-드론-입문용/2826/category/184/display/1/",
      "images": {
        "thumb": "https://media.nadaun.co/shop/thumbnails/dji/clmedia-2826.webp",
        "main": [
          "https://media.nadaun.co/shop/images/dji/clmedia-2826/main_1.webp",
          "https://media.nadaun.co/shop/images/dji/clmedia-2826/main_2.webp"
        ],
        "detail": [
          "https://media.nadaun.co/shop/detail/dji/clmedia-2826/01.webp",
          "https://media.nadaun.co/shop/detail/dji/clmedia-2826/03.webp",
          "https://media.nadaun.co/shop/detail/dji/clmedia-2826/05.webp",
          "https://media.nadaun.co/shop/detail/dji/clmedia-2826/06.webp",
          "https://media.nadaun.co/shop/detail/dji/clmedia-2826/07.webp",
          "https://media.nadaun.co/shop/detail/dji/clmedia-2826/08.webp",
          "https://media.nadaun.co/shop/detail/dji/clmedia-2826/09.webp",
          "https://media.nadaun.co/shop/detail/dji/clmedia-2826/10.webp",
          "https://media.nadaun.co/shop/detail/dji/clmedia-2826/11.webp",
          "https://media.nadaun.co/shop/detail/dji/clmedia-2826/12.webp",
          "https://media.nadaun.co/shop/detail/dji/clmedia-2826/13.webp",
          "https://media.nadaun.co/shop/detail/dji/clmedia-2826/15.webp",
          "https://media.nadaun.co/shop/detail/dji/clmedia-2826/17.webp",
          "https://media.nadaun.co/shop/detail/dji/clmedia-2826/18.webp"
        ]
      }
    },
    "clmedia-2809": {
      "id": "clmedia-2809",
      "source": "clmedia",
      "source_id": "2809",
      "name": "DJI Osmo Pocket 4 크리에이터 콤보",
      "brand": "DJI",
      "brand_slug": "dji",
      "category": "CameraSupport",
      "cat_path": [
        "CameraSupport"
      ],
      "price": 835000,
      "source_url": "https://www.clmedia.co.kr/product/dji-osmo-pocket-4-크리에이터-콤보/2809/category/184/display/1/",
      "images": {
        "thumb": "https://media.nadaun.co/shop/thumbnails/dji/clmedia-2809.webp",
        "main": [
          "https://media.nadaun.co/shop/images/dji/clmedia-2809/main_1.webp",
          "https://media.nadaun.co/shop/images/dji/clmedia-2809/main_2.webp",
          "https://media.nadaun.co/shop/images/dji/clmedia-2809/main_3.webp",
          "https://media.nadaun.co/shop/images/dji/clmedia-2809/main_4.webp",
          "https://media.nadaun.co/shop/images/dji/clmedia-2809/main_5.webp",
          "https://media.nadaun.co/shop/images/dji/clmedia-2809/main_6.webp",
          "https://media.nadaun.co/shop/images/dji/clmedia-2809/main_7.webp",
          "https://media.nadaun.co/shop/images/dji/clmedia-2809/main_8.webp"
        ],
        "detail": [
          "https://media.nadaun.co/shop/detail/dji/clmedia-2809/01.webp",
          "https://media.nadaun.co/shop/detail/dji/clmedia-2809/03.webp",
          "https://media.nadaun.co/shop/detail/dji/clmedia-2809/04.webp",
          "https://media.nadaun.co/shop/detail/dji/clmedia-2809/05.webp",
          "https://media.nadaun.co/shop/detail/dji/clmedia-2809/06.webp",
          "https://media.nadaun.co/shop/detail/dji/clmedia-2809/07.webp",
          "https://media.nadaun.co/shop/detail/dji/clmedia-2809/08.webp",
          "https://media.nadaun.co/shop/detail/dji/clmedia-2809/09.webp",
          "https://media.nadaun.co/shop/detail/dji/clmedia-2809/11.webp",
          "https://media.nadaun.co/shop/detail/dji/clmedia-2809/13.webp",
          "https://media.nadaun.co/shop/detail/dji/clmedia-2809/14.webp"
        ]
      }
    },
    "clmedia-2757": {
      "id": "clmedia-2757",
      "source": "clmedia",
      "source_id": "2757",
      "name": "디제이아이 Avata 360 아바타360 모션 플라이 모어 콤보 드론 Goggles N3 포함",
      "brand": "디제이아이",
      "brand_slug": "dji",
      "category": "Camera",
      "cat_path": [
        "Camera"
      ],
      "price": 1157000,
      "source_url": "https://www.clmedia.co.kr/product/디제이아이-avata-360-아바타360-모션-플라이-모어-콤보-드론-goggles-n3-포함/2757/category/136/display/1/",
      "images": {
        "thumb": "https://media.nadaun.co/shop/thumbnails/dji/clmedia-2757.webp",
        "main": [
          "https://media.nadaun.co/shop/images/dji/clmedia-2757/main_1.webp",
          "https://media.nadaun.co/shop/images/dji/clmedia-2757/main_2.webp"
        ],
        "detail": [
          "https://media.nadaun.co/shop/detail/dji/clmedia-2757/01.webp",
          "https://media.nadaun.co/shop/detail/dji/clmedia-2757/03.webp",
          "https://media.nadaun.co/shop/detail/dji/clmedia-2757/05.webp",
          "https://media.nadaun.co/shop/detail/dji/clmedia-2757/06.webp",
          "https://media.nadaun.co/shop/detail/dji/clmedia-2757/07.webp",
          "https://media.nadaun.co/shop/detail/dji/clmedia-2757/08.webp",
          "https://media.nadaun.co/shop/detail/dji/clmedia-2757/09.webp",
          "https://media.nadaun.co/shop/detail/dji/clmedia-2757/10.webp",
          "https://media.nadaun.co/shop/detail/dji/clmedia-2757/11.webp",
          "https://media.nadaun.co/shop/detail/dji/clmedia-2757/12.webp",
          "https://media.nadaun.co/shop/detail/dji/clmedia-2757/13.webp",
          "https://media.nadaun.co/shop/detail/dji/clmedia-2757/14.webp",
          "https://media.nadaun.co/shop/detail/dji/clmedia-2757/15.webp",
          "https://media.nadaun.co/shop/detail/dji/clmedia-2757/16.webp",
          "https://media.nadaun.co/shop/detail/dji/clmedia-2757/18.webp",
          "https://media.nadaun.co/shop/detail/dji/clmedia-2757/19.webp"
        ]
      }
    },
    "clmedia-2756": {
      "id": "clmedia-2756",
      "source": "clmedia",
      "source_id": "2756",
      "name": "디제이아이 Avata 360 아바타360 플라이 모어 콤보 드론 RC2 포함",
      "brand": "디제이아이",
      "brand_slug": "dji",
      "category": "Camera",
      "cat_path": [
        "Camera"
      ],
      "price": 1157000,
      "source_url": "https://www.clmedia.co.kr/product/디제이아이-avata-360-아바타360-플라이-모어-콤보-드론-rc2-포함/2756/category/136/display/1/",
      "images": {
        "thumb": "https://media.nadaun.co/shop/thumbnails/dji/clmedia-2756.webp",
        "main": [
          "https://media.nadaun.co/shop/images/dji/clmedia-2756/main_1.webp",
          "https://media.nadaun.co/shop/images/dji/clmedia-2756/main_2.webp"
        ],
        "detail": [
          "https://media.nadaun.co/shop/detail/dji/clmedia-2756/01.webp",
          "https://media.nadaun.co/shop/detail/dji/clmedia-2756/03.webp",
          "https://media.nadaun.co/shop/detail/dji/clmedia-2756/05.webp",
          "https://media.nadaun.co/shop/detail/dji/clmedia-2756/06.webp",
          "https://media.nadaun.co/shop/detail/dji/clmedia-2756/07.webp",
          "https://media.nadaun.co/shop/detail/dji/clmedia-2756/08.webp",
          "https://media.nadaun.co/shop/detail/dji/clmedia-2756/09.webp",
          "https://media.nadaun.co/shop/detail/dji/clmedia-2756/10.webp",
          "https://media.nadaun.co/shop/detail/dji/clmedia-2756/11.webp",
          "https://media.nadaun.co/shop/detail/dji/clmedia-2756/12.webp",
          "https://media.nadaun.co/shop/detail/dji/clmedia-2756/13.webp",
          "https://media.nadaun.co/shop/detail/dji/clmedia-2756/14.webp",
          "https://media.nadaun.co/shop/detail/dji/clmedia-2756/15.webp",
          "https://media.nadaun.co/shop/detail/dji/clmedia-2756/16.webp",
          "https://media.nadaun.co/shop/detail/dji/clmedia-2756/18.webp",
          "https://media.nadaun.co/shop/detail/dji/clmedia-2756/19.webp"
        ]
      }
    },
    "clmedia-2755": {
      "id": "clmedia-2755",
      "source": "clmedia",
      "source_id": "2755",
      "name": "디제이아이 Avata 360 아바타360 드론 RC2 포함",
      "brand": "디제이아이",
      "brand_slug": "dji",
      "category": "Camera",
      "cat_path": [
        "Camera"
      ],
      "price": 925000,
      "source_url": "https://www.clmedia.co.kr/product/디제이아이-avata-360-아바타360-드론-rc2-포함/2755/category/136/display/1/",
      "images": {
        "thumb": "https://media.nadaun.co/shop/thumbnails/dji/clmedia-2755.webp",
        "main": [
          "https://media.nadaun.co/shop/images/dji/clmedia-2755/main_1.webp",
          "https://media.nadaun.co/shop/images/dji/clmedia-2755/main_2.webp"
        ],
        "detail": [
          "https://media.nadaun.co/shop/detail/dji/clmedia-2755/01.webp",
          "https://media.nadaun.co/shop/detail/dji/clmedia-2755/03.webp",
          "https://media.nadaun.co/shop/detail/dji/clmedia-2755/05.webp",
          "https://media.nadaun.co/shop/detail/dji/clmedia-2755/06.webp",
          "https://media.nadaun.co/shop/detail/dji/clmedia-2755/07.webp",
          "https://media.nadaun.co/shop/detail/dji/clmedia-2755/08.webp",
          "https://media.nadaun.co/shop/detail/dji/clmedia-2755/09.webp",
          "https://media.nadaun.co/shop/detail/dji/clmedia-2755/10.webp",
          "https://media.nadaun.co/shop/detail/dji/clmedia-2755/11.webp",
          "https://media.nadaun.co/shop/detail/dji/clmedia-2755/12.webp",
          "https://media.nadaun.co/shop/detail/dji/clmedia-2755/13.webp",
          "https://media.nadaun.co/shop/detail/dji/clmedia-2755/14.webp",
          "https://media.nadaun.co/shop/detail/dji/clmedia-2755/15.webp",
          "https://media.nadaun.co/shop/detail/dji/clmedia-2755/16.webp",
          "https://media.nadaun.co/shop/detail/dji/clmedia-2755/18.webp",
          "https://media.nadaun.co/shop/detail/dji/clmedia-2755/19.webp"
        ]
      }
    },
    "clmedia-2645": {
      "id": "clmedia-2645",
      "source": "clmedia",
      "source_id": "2645",
      "name": "DJI RS5 단품 카메라 짐벌",
      "brand": "DJI",
      "brand_slug": "dji",
      "category": "CameraSupport",
      "cat_path": [
        "CameraSupport"
      ],
      "price": 654000,
      "source_url": "https://www.clmedia.co.kr/product/dji-rs5-단품-카메라-짐벌/2645/category/184/display/1/",
      "images": {
        "thumb": "https://media.nadaun.co/shop/thumbnails/dji/clmedia-2645.webp",
        "main": [
          "https://media.nadaun.co/shop/images/dji/clmedia-2645/main_1.webp",
          "https://media.nadaun.co/shop/images/dji/clmedia-2645/main_2.webp"
        ],
        "detail": [
          "https://media.nadaun.co/shop/detail/dji/clmedia-2645/01.webp",
          "https://media.nadaun.co/shop/detail/dji/clmedia-2645/03.webp",
          "https://media.nadaun.co/shop/detail/dji/clmedia-2645/05.webp",
          "https://media.nadaun.co/shop/detail/dji/clmedia-2645/06.webp",
          "https://media.nadaun.co/shop/detail/dji/clmedia-2645/07.webp",
          "https://media.nadaun.co/shop/detail/dji/clmedia-2645/08.webp",
          "https://media.nadaun.co/shop/detail/dji/clmedia-2645/09.webp",
          "https://media.nadaun.co/shop/detail/dji/clmedia-2645/10.webp",
          "https://media.nadaun.co/shop/detail/dji/clmedia-2645/11.webp",
          "https://media.nadaun.co/shop/detail/dji/clmedia-2645/12.webp",
          "https://media.nadaun.co/shop/detail/dji/clmedia-2645/13.webp",
          "https://media.nadaun.co/shop/detail/dji/clmedia-2645/14.webp",
          "https://media.nadaun.co/shop/detail/dji/clmedia-2645/15.webp",
          "https://media.nadaun.co/shop/detail/dji/clmedia-2645/17.webp",
          "https://media.nadaun.co/shop/detail/dji/clmedia-2645/18.webp"
        ]
      }
    },
    "clmedia-2644": {
      "id": "clmedia-2644",
      "source": "clmedia",
      "source_id": "2644",
      "name": "DJI RS5 콤보 카메라 짐벌",
      "brand": "DJI",
      "brand_slug": "dji",
      "category": "CameraSupport",
      "cat_path": [
        "CameraSupport"
      ],
      "price": 823000,
      "source_url": "https://www.clmedia.co.kr/product/dji-rs5-콤보-카메라-짐벌/2644/category/184/display/1/",
      "images": {
        "thumb": "https://media.nadaun.co/shop/thumbnails/dji/clmedia-2644.webp",
        "main": [
          "https://media.nadaun.co/shop/images/dji/clmedia-2644/main_1.webp",
          "https://media.nadaun.co/shop/images/dji/clmedia-2644/main_2.webp"
        ],
        "detail": [
          "https://media.nadaun.co/shop/detail/dji/clmedia-2644/01.webp",
          "https://media.nadaun.co/shop/detail/dji/clmedia-2644/03.webp",
          "https://media.nadaun.co/shop/detail/dji/clmedia-2644/05.webp",
          "https://media.nadaun.co/shop/detail/dji/clmedia-2644/06.webp",
          "https://media.nadaun.co/shop/detail/dji/clmedia-2644/07.webp",
          "https://media.nadaun.co/shop/detail/dji/clmedia-2644/08.webp",
          "https://media.nadaun.co/shop/detail/dji/clmedia-2644/09.webp",
          "https://media.nadaun.co/shop/detail/dji/clmedia-2644/10.webp",
          "https://media.nadaun.co/shop/detail/dji/clmedia-2644/11.webp",
          "https://media.nadaun.co/shop/detail/dji/clmedia-2644/12.webp",
          "https://media.nadaun.co/shop/detail/dji/clmedia-2644/13.webp",
          "https://media.nadaun.co/shop/detail/dji/clmedia-2644/14.webp",
          "https://media.nadaun.co/shop/detail/dji/clmedia-2644/15.webp",
          "https://media.nadaun.co/shop/detail/dji/clmedia-2644/17.webp",
          "https://media.nadaun.co/shop/detail/dji/clmedia-2644/18.webp"
        ]
      }
    },
    "clmedia-2453": {
      "id": "clmedia-2453",
      "source": "clmedia",
      "source_id": "2453",
      "name": "디제이아이 오즈모 액션6 스탠더드 콤보",
      "brand": "디제이아이",
      "brand_slug": "dji",
      "category": "Camera",
      "cat_path": [
        "Camera"
      ],
      "price": 578000,
      "source_url": "https://www.clmedia.co.kr/product/디제이아이-오즈모-액션6-스탠더드-콤보/2453/category/136/display/1/",
      "images": {
        "thumb": "https://media.nadaun.co/shop/thumbnails/dji/clmedia-2453.webp",
        "main": [
          "https://media.nadaun.co/shop/images/dji/clmedia-2453/main_1.webp",
          "https://media.nadaun.co/shop/images/dji/clmedia-2453/main_2.webp",
          "https://media.nadaun.co/shop/images/dji/clmedia-2453/main_3.webp",
          "https://media.nadaun.co/shop/images/dji/clmedia-2453/main_4.webp",
          "https://media.nadaun.co/shop/images/dji/clmedia-2453/main_5.webp",
          "https://media.nadaun.co/shop/images/dji/clmedia-2453/main_6.webp",
          "https://media.nadaun.co/shop/images/dji/clmedia-2453/main_7.webp",
          "https://media.nadaun.co/shop/images/dji/clmedia-2453/main_8.webp"
        ],
        "detail": [
          "https://media.nadaun.co/shop/detail/dji/clmedia-2453/01.webp",
          "https://media.nadaun.co/shop/detail/dji/clmedia-2453/03.webp",
          "https://media.nadaun.co/shop/detail/dji/clmedia-2453/04.webp",
          "https://media.nadaun.co/shop/detail/dji/clmedia-2453/05.webp",
          "https://media.nadaun.co/shop/detail/dji/clmedia-2453/06.webp",
          "https://media.nadaun.co/shop/detail/dji/clmedia-2453/07.webp",
          "https://media.nadaun.co/shop/detail/dji/clmedia-2453/08.webp",
          "https://media.nadaun.co/shop/detail/dji/clmedia-2453/09.webp",
          "https://media.nadaun.co/shop/detail/dji/clmedia-2453/11.webp",
          "https://media.nadaun.co/shop/detail/dji/clmedia-2453/12.webp",
          "https://media.nadaun.co/shop/detail/dji/clmedia-2453/13.webp",
          "https://media.nadaun.co/shop/detail/dji/clmedia-2453/14.webp",
          "https://media.nadaun.co/shop/detail/dji/clmedia-2453/15.webp",
          "https://media.nadaun.co/shop/detail/dji/clmedia-2453/16.webp",
          "https://media.nadaun.co/shop/detail/dji/clmedia-2453/17.webp",
          "https://media.nadaun.co/shop/detail/dji/clmedia-2453/18.webp",
          "https://media.nadaun.co/shop/detail/dji/clmedia-2453/19.webp",
          "https://media.nadaun.co/shop/detail/dji/clmedia-2453/20.webp",
          "https://media.nadaun.co/shop/detail/dji/clmedia-2453/21.webp",
          "https://media.nadaun.co/shop/detail/dji/clmedia-2453/22.webp",
          "https://media.nadaun.co/shop/detail/dji/clmedia-2453/23.webp",
          "https://media.nadaun.co/shop/detail/dji/clmedia-2453/24.webp",
          "https://media.nadaun.co/shop/detail/dji/clmedia-2453/25.webp",
          "https://media.nadaun.co/shop/detail/dji/clmedia-2453/26.webp",
          "https://media.nadaun.co/shop/detail/dji/clmedia-2453/27.webp",
          "https://media.nadaun.co/shop/detail/dji/clmedia-2453/29.webp",
          "https://media.nadaun.co/shop/detail/dji/clmedia-2453/30.webp",
          "https://media.nadaun.co/shop/detail/dji/clmedia-2453/31.webp"
        ]
      }
    },
    "clmedia-2452": {
      "id": "clmedia-2452",
      "source": "clmedia",
      "source_id": "2452",
      "name": "디제이아이 오즈모 액션6 어드벤쳐 콤보",
      "brand": "디제이아이",
      "brand_slug": "dji",
      "category": "Camera",
      "cat_path": [
        "Camera"
      ],
      "price": 713000,
      "source_url": "https://www.clmedia.co.kr/product/디제이아이-오즈모-액션6-어드벤쳐-콤보/2452/category/136/display/1/",
      "images": {
        "thumb": "https://media.nadaun.co/shop/thumbnails/dji/clmedia-2452.webp",
        "main": [
          "https://media.nadaun.co/shop/images/dji/clmedia-2452/main_1.webp",
          "https://media.nadaun.co/shop/images/dji/clmedia-2452/main_2.webp",
          "https://media.nadaun.co/shop/images/dji/clmedia-2452/main_3.webp",
          "https://media.nadaun.co/shop/images/dji/clmedia-2452/main_4.webp",
          "https://media.nadaun.co/shop/images/dji/clmedia-2452/main_5.webp",
          "https://media.nadaun.co/shop/images/dji/clmedia-2452/main_6.webp",
          "https://media.nadaun.co/shop/images/dji/clmedia-2452/main_7.webp",
          "https://media.nadaun.co/shop/images/dji/clmedia-2452/main_8.webp"
        ],
        "detail": [
          "https://media.nadaun.co/shop/detail/dji/clmedia-2452/01.webp",
          "https://media.nadaun.co/shop/detail/dji/clmedia-2452/03.webp",
          "https://media.nadaun.co/shop/detail/dji/clmedia-2452/04.webp",
          "https://media.nadaun.co/shop/detail/dji/clmedia-2452/05.webp",
          "https://media.nadaun.co/shop/detail/dji/clmedia-2452/06.webp",
          "https://media.nadaun.co/shop/detail/dji/clmedia-2452/07.webp",
          "https://media.nadaun.co/shop/detail/dji/clmedia-2452/08.webp",
          "https://media.nadaun.co/shop/detail/dji/clmedia-2452/09.webp",
          "https://media.nadaun.co/shop/detail/dji/clmedia-2452/11.webp",
          "https://media.nadaun.co/shop/detail/dji/clmedia-2452/12.webp",
          "https://media.nadaun.co/shop/detail/dji/clmedia-2452/13.webp",
          "https://media.nadaun.co/shop/detail/dji/clmedia-2452/14.webp",
          "https://media.nadaun.co/shop/detail/dji/clmedia-2452/15.webp",
          "https://media.nadaun.co/shop/detail/dji/clmedia-2452/16.webp",
          "https://media.nadaun.co/shop/detail/dji/clmedia-2452/17.webp",
          "https://media.nadaun.co/shop/detail/dji/clmedia-2452/18.webp",
          "https://media.nadaun.co/shop/detail/dji/clmedia-2452/19.webp",
          "https://media.nadaun.co/shop/detail/dji/clmedia-2452/20.webp",
          "https://media.nadaun.co/shop/detail/dji/clmedia-2452/21.webp",
          "https://media.nadaun.co/shop/detail/dji/clmedia-2452/22.webp",
          "https://media.nadaun.co/shop/detail/dji/clmedia-2452/23.webp",
          "https://media.nadaun.co/shop/detail/dji/clmedia-2452/24.webp",
          "https://media.nadaun.co/shop/detail/dji/clmedia-2452/25.webp",
          "https://media.nadaun.co/shop/detail/dji/clmedia-2452/26.webp",
          "https://media.nadaun.co/shop/detail/dji/clmedia-2452/27.webp",
          "https://media.nadaun.co/shop/detail/dji/clmedia-2452/29.webp",
          "https://media.nadaun.co/shop/detail/dji/clmedia-2452/30.webp"
        ]
      }
    },
    "clmedia-2434": {
      "id": "clmedia-2434",
      "source": "clmedia",
      "source_id": "2434",
      "name": "디제이아이 OSMO MOBILE8 오즈모 모바일8 고급 추적 콤보 스마트폰 짐벌",
      "brand": "디제이아이",
      "brand_slug": "dji",
      "category": "Camera",
      "cat_path": [
        "Camera"
      ],
      "price": 176000,
      "source_url": "https://www.clmedia.co.kr/product/디제이아이-osmo-mobile8-오즈모-모바일8-고급-추적-콤보-스마트폰-짐벌/2434/category/136/display/1/",
      "images": {
        "thumb": "https://media.nadaun.co/shop/thumbnails/dji/clmedia-2434.webp",
        "main": [
          "https://media.nadaun.co/shop/images/dji/clmedia-2434/main_1.webp",
          "https://media.nadaun.co/shop/images/dji/clmedia-2434/main_2.webp",
          "https://media.nadaun.co/shop/images/dji/clmedia-2434/main_3.webp",
          "https://media.nadaun.co/shop/images/dji/clmedia-2434/main_4.webp",
          "https://media.nadaun.co/shop/images/dji/clmedia-2434/main_5.webp",
          "https://media.nadaun.co/shop/images/dji/clmedia-2434/main_6.webp",
          "https://media.nadaun.co/shop/images/dji/clmedia-2434/main_7.webp"
        ],
        "detail": [
          "https://media.nadaun.co/shop/detail/dji/clmedia-2434/01.webp",
          "https://media.nadaun.co/shop/detail/dji/clmedia-2434/03.webp",
          "https://media.nadaun.co/shop/detail/dji/clmedia-2434/04.webp",
          "https://media.nadaun.co/shop/detail/dji/clmedia-2434/05.webp",
          "https://media.nadaun.co/shop/detail/dji/clmedia-2434/06.webp",
          "https://media.nadaun.co/shop/detail/dji/clmedia-2434/07.webp",
          "https://media.nadaun.co/shop/detail/dji/clmedia-2434/08.webp",
          "https://media.nadaun.co/shop/detail/dji/clmedia-2434/24.webp",
          "https://media.nadaun.co/shop/detail/dji/clmedia-2434/26.webp",
          "https://media.nadaun.co/shop/detail/dji/clmedia-2434/27.webp"
        ]
      }
    },
    "clmedia-2328": {
      "id": "clmedia-2328",
      "source": "clmedia",
      "source_id": "2328",
      "name": "디제이아이 DJON64G OSMO NANO 스탠다드콤보(64GB)",
      "brand": "디제이아이",
      "brand_slug": "dji",
      "category": "Camera",
      "cat_path": [
        "Camera"
      ],
      "price": 389000,
      "source_url": "https://www.clmedia.co.kr/product/디제이아이-djon64g-osmo-nano-스탠다드콤보64gb/2328/category/136/display/1/",
      "images": {
        "thumb": "https://media.nadaun.co/shop/thumbnails/dji/clmedia-2328.webp",
        "main": [
          "https://media.nadaun.co/shop/images/dji/clmedia-2328/main_1.webp",
          "https://media.nadaun.co/shop/images/dji/clmedia-2328/main_2.webp",
          "https://media.nadaun.co/shop/images/dji/clmedia-2328/main_3.webp",
          "https://media.nadaun.co/shop/images/dji/clmedia-2328/main_4.webp",
          "https://media.nadaun.co/shop/images/dji/clmedia-2328/main_5.webp",
          "https://media.nadaun.co/shop/images/dji/clmedia-2328/main_6.webp",
          "https://media.nadaun.co/shop/images/dji/clmedia-2328/main_7.webp",
          "https://media.nadaun.co/shop/images/dji/clmedia-2328/main_8.webp"
        ],
        "detail": [
          "https://media.nadaun.co/shop/detail/dji/clmedia-2328/01.webp",
          "https://media.nadaun.co/shop/detail/dji/clmedia-2328/03.webp",
          "https://media.nadaun.co/shop/detail/dji/clmedia-2328/04.webp",
          "https://media.nadaun.co/shop/detail/dji/clmedia-2328/05.webp",
          "https://media.nadaun.co/shop/detail/dji/clmedia-2328/06.webp",
          "https://media.nadaun.co/shop/detail/dji/clmedia-2328/07.webp",
          "https://media.nadaun.co/shop/detail/dji/clmedia-2328/08.webp",
          "https://media.nadaun.co/shop/detail/dji/clmedia-2328/09.webp",
          "https://media.nadaun.co/shop/detail/dji/clmedia-2328/11.webp",
          "https://media.nadaun.co/shop/detail/dji/clmedia-2328/12.webp",
          "https://media.nadaun.co/shop/detail/dji/clmedia-2328/13.webp",
          "https://media.nadaun.co/shop/detail/dji/clmedia-2328/14.webp",
          "https://media.nadaun.co/shop/detail/dji/clmedia-2328/15.webp",
          "https://media.nadaun.co/shop/detail/dji/clmedia-2328/16.webp",
          "https://media.nadaun.co/shop/detail/dji/clmedia-2328/17.webp",
          "https://media.nadaun.co/shop/detail/dji/clmedia-2328/18.webp",
          "https://media.nadaun.co/shop/detail/dji/clmedia-2328/19.webp",
          "https://media.nadaun.co/shop/detail/dji/clmedia-2328/20.webp",
          "https://media.nadaun.co/shop/detail/dji/clmedia-2328/21.webp",
          "https://media.nadaun.co/shop/detail/dji/clmedia-2328/22.webp",
          "https://media.nadaun.co/shop/detail/dji/clmedia-2328/24.webp",
          "https://media.nadaun.co/shop/detail/dji/clmedia-2328/25.webp",
          "https://media.nadaun.co/shop/detail/dji/clmedia-2328/26.webp"
        ]
      }
    },
    "clmedia-2327": {
      "id": "clmedia-2327",
      "source": "clmedia",
      "source_id": "2327",
      "name": "디제이아이 DJON128G OSMO NANO 스탠다드콤보(128GB)",
      "brand": "디제이아이",
      "brand_slug": "dji",
      "category": "Camera",
      "cat_path": [
        "Camera"
      ],
      "price": 449000,
      "source_url": "https://www.clmedia.co.kr/product/디제이아이-djon128g-osmo-nano-스탠다드콤보128gb/2327/category/136/display/1/",
      "images": {
        "thumb": "https://media.nadaun.co/shop/thumbnails/dji/clmedia-2327.webp",
        "main": [
          "https://media.nadaun.co/shop/images/dji/clmedia-2327/main_1.webp",
          "https://media.nadaun.co/shop/images/dji/clmedia-2327/main_2.webp",
          "https://media.nadaun.co/shop/images/dji/clmedia-2327/main_3.webp",
          "https://media.nadaun.co/shop/images/dji/clmedia-2327/main_4.webp",
          "https://media.nadaun.co/shop/images/dji/clmedia-2327/main_5.webp",
          "https://media.nadaun.co/shop/images/dji/clmedia-2327/main_6.webp",
          "https://media.nadaun.co/shop/images/dji/clmedia-2327/main_7.webp",
          "https://media.nadaun.co/shop/images/dji/clmedia-2327/main_8.webp"
        ],
        "detail": [
          "https://media.nadaun.co/shop/detail/dji/clmedia-2327/01.webp",
          "https://media.nadaun.co/shop/detail/dji/clmedia-2327/03.webp",
          "https://media.nadaun.co/shop/detail/dji/clmedia-2327/04.webp",
          "https://media.nadaun.co/shop/detail/dji/clmedia-2327/05.webp",
          "https://media.nadaun.co/shop/detail/dji/clmedia-2327/06.webp",
          "https://media.nadaun.co/shop/detail/dji/clmedia-2327/07.webp",
          "https://media.nadaun.co/shop/detail/dji/clmedia-2327/08.webp",
          "https://media.nadaun.co/shop/detail/dji/clmedia-2327/09.webp",
          "https://media.nadaun.co/shop/detail/dji/clmedia-2327/11.webp",
          "https://media.nadaun.co/shop/detail/dji/clmedia-2327/12.webp",
          "https://media.nadaun.co/shop/detail/dji/clmedia-2327/13.webp",
          "https://media.nadaun.co/shop/detail/dji/clmedia-2327/14.webp",
          "https://media.nadaun.co/shop/detail/dji/clmedia-2327/15.webp",
          "https://media.nadaun.co/shop/detail/dji/clmedia-2327/16.webp",
          "https://media.nadaun.co/shop/detail/dji/clmedia-2327/17.webp",
          "https://media.nadaun.co/shop/detail/dji/clmedia-2327/18.webp",
          "https://media.nadaun.co/shop/detail/dji/clmedia-2327/19.webp",
          "https://media.nadaun.co/shop/detail/dji/clmedia-2327/20.webp",
          "https://media.nadaun.co/shop/detail/dji/clmedia-2327/21.webp",
          "https://media.nadaun.co/shop/detail/dji/clmedia-2327/22.webp",
          "https://media.nadaun.co/shop/detail/dji/clmedia-2327/24.webp",
          "https://media.nadaun.co/shop/detail/dji/clmedia-2327/25.webp",
          "https://media.nadaun.co/shop/detail/dji/clmedia-2327/26.webp"
        ]
      }
    },
    "clmedia-2316": {
      "id": "clmedia-2316",
      "source": "clmedia",
      "source_id": "2316",
      "name": "디제이아이 미니5프로",
      "brand": "디제이아이",
      "brand_slug": "dji",
      "category": "Camera",
      "cat_path": [
        "Camera"
      ],
      "price": 1030000,
      "source_url": "https://www.clmedia.co.kr/product/디제이아이-미니5프로/2316/category/136/display/1/",
      "images": {
        "thumb": "https://media.nadaun.co/shop/thumbnails/dji/clmedia-2316.webp",
        "main": [
          "https://media.nadaun.co/shop/images/dji/clmedia-2316/main_1.webp",
          "https://media.nadaun.co/shop/images/dji/clmedia-2316/main_2.webp",
          "https://media.nadaun.co/shop/images/dji/clmedia-2316/main_3.webp",
          "https://media.nadaun.co/shop/images/dji/clmedia-2316/main_4.webp",
          "https://media.nadaun.co/shop/images/dji/clmedia-2316/main_5.webp",
          "https://media.nadaun.co/shop/images/dji/clmedia-2316/main_6.webp",
          "https://media.nadaun.co/shop/images/dji/clmedia-2316/main_7.webp"
        ],
        "detail": [
          "https://media.nadaun.co/shop/detail/dji/clmedia-2316/01.webp",
          "https://media.nadaun.co/shop/detail/dji/clmedia-2316/03.webp",
          "https://media.nadaun.co/shop/detail/dji/clmedia-2316/04.webp",
          "https://media.nadaun.co/shop/detail/dji/clmedia-2316/05.webp",
          "https://media.nadaun.co/shop/detail/dji/clmedia-2316/06.webp",
          "https://media.nadaun.co/shop/detail/dji/clmedia-2316/07.webp",
          "https://media.nadaun.co/shop/detail/dji/clmedia-2316/08.webp",
          "https://media.nadaun.co/shop/detail/dji/clmedia-2316/10.webp",
          "https://media.nadaun.co/shop/detail/dji/clmedia-2316/11.webp",
          "https://media.nadaun.co/shop/detail/dji/clmedia-2316/12.webp",
          "https://media.nadaun.co/shop/detail/dji/clmedia-2316/13.webp",
          "https://media.nadaun.co/shop/detail/dji/clmedia-2316/14.webp",
          "https://media.nadaun.co/shop/detail/dji/clmedia-2316/15.webp",
          "https://media.nadaun.co/shop/detail/dji/clmedia-2316/16.webp",
          "https://media.nadaun.co/shop/detail/dji/clmedia-2316/17.webp",
          "https://media.nadaun.co/shop/detail/dji/clmedia-2316/18.webp",
          "https://media.nadaun.co/shop/detail/dji/clmedia-2316/19.webp",
          "https://media.nadaun.co/shop/detail/dji/clmedia-2316/20.webp",
          "https://media.nadaun.co/shop/detail/dji/clmedia-2316/22.webp",
          "https://media.nadaun.co/shop/detail/dji/clmedia-2316/23.webp",
          "https://media.nadaun.co/shop/detail/dji/clmedia-2316/24.webp"
        ]
      }
    },
    "clmedia-2296": {
      "id": "clmedia-2296",
      "source": "clmedia",
      "source_id": "2296",
      "name": "디제이아이 미니5프로 플라이모어 콤보(DJI RC-N3 포함)",
      "brand": "디제이아이",
      "brand_slug": "dji",
      "category": "Camera",
      "cat_path": [
        "Camera"
      ],
      "price": 1290000,
      "source_url": "https://www.clmedia.co.kr/product/디제이아이-미니5프로-플라이모어-콤보dji-rc-n3-포함/2296/category/136/display/1/",
      "images": {
        "thumb": "https://media.nadaun.co/shop/thumbnails/dji/clmedia-2296.webp",
        "main": [
          "https://media.nadaun.co/shop/images/dji/clmedia-2296/main_1.webp",
          "https://media.nadaun.co/shop/images/dji/clmedia-2296/main_2.webp",
          "https://media.nadaun.co/shop/images/dji/clmedia-2296/main_3.webp",
          "https://media.nadaun.co/shop/images/dji/clmedia-2296/main_4.webp",
          "https://media.nadaun.co/shop/images/dji/clmedia-2296/main_5.webp",
          "https://media.nadaun.co/shop/images/dji/clmedia-2296/main_6.webp",
          "https://media.nadaun.co/shop/images/dji/clmedia-2296/main_7.webp"
        ],
        "detail": [
          "https://media.nadaun.co/shop/detail/dji/clmedia-2296/01.webp",
          "https://media.nadaun.co/shop/detail/dji/clmedia-2296/03.webp",
          "https://media.nadaun.co/shop/detail/dji/clmedia-2296/04.webp",
          "https://media.nadaun.co/shop/detail/dji/clmedia-2296/05.webp",
          "https://media.nadaun.co/shop/detail/dji/clmedia-2296/06.webp",
          "https://media.nadaun.co/shop/detail/dji/clmedia-2296/07.webp",
          "https://media.nadaun.co/shop/detail/dji/clmedia-2296/08.webp",
          "https://media.nadaun.co/shop/detail/dji/clmedia-2296/10.webp",
          "https://media.nadaun.co/shop/detail/dji/clmedia-2296/11.webp",
          "https://media.nadaun.co/shop/detail/dji/clmedia-2296/12.webp",
          "https://media.nadaun.co/shop/detail/dji/clmedia-2296/13.webp",
          "https://media.nadaun.co/shop/detail/dji/clmedia-2296/14.webp",
          "https://media.nadaun.co/shop/detail/dji/clmedia-2296/15.webp",
          "https://media.nadaun.co/shop/detail/dji/clmedia-2296/16.webp",
          "https://media.nadaun.co/shop/detail/dji/clmedia-2296/17.webp",
          "https://media.nadaun.co/shop/detail/dji/clmedia-2296/18.webp",
          "https://media.nadaun.co/shop/detail/dji/clmedia-2296/19.webp",
          "https://media.nadaun.co/shop/detail/dji/clmedia-2296/20.webp",
          "https://media.nadaun.co/shop/detail/dji/clmedia-2296/22.webp",
          "https://media.nadaun.co/shop/detail/dji/clmedia-2296/23.webp",
          "https://media.nadaun.co/shop/detail/dji/clmedia-2296/24.webp"
        ]
      }
    },
    "clmedia-2295": {
      "id": "clmedia-2295",
      "source": "clmedia",
      "source_id": "2295",
      "name": "디제이아이 미니5프로 플라이모어 콤보(DJI RC2 포함)",
      "brand": "디제이아이",
      "brand_slug": "dji",
      "category": "Camera",
      "cat_path": [
        "Camera"
      ],
      "price": 1510000,
      "source_url": "https://www.clmedia.co.kr/product/디제이아이-미니5프로-플라이모어-콤보dji-rc2-포함/2295/category/136/display/1/",
      "images": {
        "thumb": "https://media.nadaun.co/shop/thumbnails/dji/clmedia-2295.webp",
        "main": [
          "https://media.nadaun.co/shop/images/dji/clmedia-2295/main_1.webp",
          "https://media.nadaun.co/shop/images/dji/clmedia-2295/main_2.webp",
          "https://media.nadaun.co/shop/images/dji/clmedia-2295/main_3.webp",
          "https://media.nadaun.co/shop/images/dji/clmedia-2295/main_4.webp",
          "https://media.nadaun.co/shop/images/dji/clmedia-2295/main_5.webp",
          "https://media.nadaun.co/shop/images/dji/clmedia-2295/main_6.webp",
          "https://media.nadaun.co/shop/images/dji/clmedia-2295/main_7.webp"
        ],
        "detail": [
          "https://media.nadaun.co/shop/detail/dji/clmedia-2295/01.webp",
          "https://media.nadaun.co/shop/detail/dji/clmedia-2295/03.webp",
          "https://media.nadaun.co/shop/detail/dji/clmedia-2295/04.webp",
          "https://media.nadaun.co/shop/detail/dji/clmedia-2295/05.webp",
          "https://media.nadaun.co/shop/detail/dji/clmedia-2295/06.webp",
          "https://media.nadaun.co/shop/detail/dji/clmedia-2295/07.webp",
          "https://media.nadaun.co/shop/detail/dji/clmedia-2295/08.webp",
          "https://media.nadaun.co/shop/detail/dji/clmedia-2295/10.webp",
          "https://media.nadaun.co/shop/detail/dji/clmedia-2295/11.webp",
          "https://media.nadaun.co/shop/detail/dji/clmedia-2295/12.webp",
          "https://media.nadaun.co/shop/detail/dji/clmedia-2295/13.webp",
          "https://media.nadaun.co/shop/detail/dji/clmedia-2295/14.webp",
          "https://media.nadaun.co/shop/detail/dji/clmedia-2295/15.webp",
          "https://media.nadaun.co/shop/detail/dji/clmedia-2295/16.webp",
          "https://media.nadaun.co/shop/detail/dji/clmedia-2295/17.webp",
          "https://media.nadaun.co/shop/detail/dji/clmedia-2295/18.webp",
          "https://media.nadaun.co/shop/detail/dji/clmedia-2295/19.webp",
          "https://media.nadaun.co/shop/detail/dji/clmedia-2295/20.webp",
          "https://media.nadaun.co/shop/detail/dji/clmedia-2295/22.webp",
          "https://media.nadaun.co/shop/detail/dji/clmedia-2295/23.webp",
          "https://media.nadaun.co/shop/detail/dji/clmedia-2295/24.webp"
        ]
      }
    },
    "clmedia-2294": {
      "id": "clmedia-2294",
      "source": "clmedia",
      "source_id": "2294",
      "name": "디제이아이 DJM5PFMCP 미니5프로 플라이모어 콤보플러스(DJI RC2 포함)",
      "brand": "디제이아이",
      "brand_slug": "dji",
      "category": "Camera",
      "cat_path": [
        "Camera"
      ],
      "price": 1660000,
      "source_url": "https://www.clmedia.co.kr/product/디제이아이-djm5pfmcp-미니5프로-플라이모어-콤보플러스dji-rc2-포함/2294/category/136/display/1/",
      "images": {
        "thumb": "https://media.nadaun.co/shop/thumbnails/dji/clmedia-2294.webp",
        "main": [
          "https://media.nadaun.co/shop/images/dji/clmedia-2294/main_1.webp",
          "https://media.nadaun.co/shop/images/dji/clmedia-2294/main_2.webp",
          "https://media.nadaun.co/shop/images/dji/clmedia-2294/main_3.webp",
          "https://media.nadaun.co/shop/images/dji/clmedia-2294/main_4.webp",
          "https://media.nadaun.co/shop/images/dji/clmedia-2294/main_5.webp",
          "https://media.nadaun.co/shop/images/dji/clmedia-2294/main_6.webp",
          "https://media.nadaun.co/shop/images/dji/clmedia-2294/main_7.webp"
        ],
        "detail": [
          "https://media.nadaun.co/shop/detail/dji/clmedia-2294/01.webp",
          "https://media.nadaun.co/shop/detail/dji/clmedia-2294/03.webp",
          "https://media.nadaun.co/shop/detail/dji/clmedia-2294/04.webp",
          "https://media.nadaun.co/shop/detail/dji/clmedia-2294/05.webp",
          "https://media.nadaun.co/shop/detail/dji/clmedia-2294/06.webp",
          "https://media.nadaun.co/shop/detail/dji/clmedia-2294/07.webp",
          "https://media.nadaun.co/shop/detail/dji/clmedia-2294/08.webp",
          "https://media.nadaun.co/shop/detail/dji/clmedia-2294/10.webp",
          "https://media.nadaun.co/shop/detail/dji/clmedia-2294/11.webp",
          "https://media.nadaun.co/shop/detail/dji/clmedia-2294/12.webp",
          "https://media.nadaun.co/shop/detail/dji/clmedia-2294/13.webp",
          "https://media.nadaun.co/shop/detail/dji/clmedia-2294/14.webp",
          "https://media.nadaun.co/shop/detail/dji/clmedia-2294/15.webp",
          "https://media.nadaun.co/shop/detail/dji/clmedia-2294/16.webp",
          "https://media.nadaun.co/shop/detail/dji/clmedia-2294/17.webp",
          "https://media.nadaun.co/shop/detail/dji/clmedia-2294/18.webp",
          "https://media.nadaun.co/shop/detail/dji/clmedia-2294/19.webp",
          "https://media.nadaun.co/shop/detail/dji/clmedia-2294/20.webp",
          "https://media.nadaun.co/shop/detail/dji/clmedia-2294/22.webp",
          "https://media.nadaun.co/shop/detail/dji/clmedia-2294/23.webp"
        ]
      }
    },
    "clmedia-2126": {
      "id": "clmedia-2126",
      "source": "clmedia",
      "source_id": "2126",
      "name": "디제이아이 DJOS360ADC 오즈모 360 어드밴처 콤보",
      "brand": "디제이아이",
      "brand_slug": "dji",
      "category": "Camera",
      "cat_path": [
        "Camera"
      ],
      "price": 770000,
      "source_url": "https://www.clmedia.co.kr/product/디제이아이-djos360adc-오즈모-360-어드밴처-콤보/2126/category/136/display/1/",
      "images": {
        "thumb": "https://media.nadaun.co/shop/thumbnails/dji/clmedia-2126.webp",
        "main": [
          "https://media.nadaun.co/shop/images/dji/clmedia-2126/main_1.webp",
          "https://media.nadaun.co/shop/images/dji/clmedia-2126/main_2.webp",
          "https://media.nadaun.co/shop/images/dji/clmedia-2126/main_3.webp",
          "https://media.nadaun.co/shop/images/dji/clmedia-2126/main_4.webp",
          "https://media.nadaun.co/shop/images/dji/clmedia-2126/main_5.webp",
          "https://media.nadaun.co/shop/images/dji/clmedia-2126/main_6.webp",
          "https://media.nadaun.co/shop/images/dji/clmedia-2126/main_7.webp",
          "https://media.nadaun.co/shop/images/dji/clmedia-2126/main_8.webp",
          "https://media.nadaun.co/shop/images/dji/clmedia-2126/main_9.webp"
        ],
        "detail": [
          "https://media.nadaun.co/shop/detail/dji/clmedia-2126/01.webp",
          "https://media.nadaun.co/shop/detail/dji/clmedia-2126/03.webp",
          "https://media.nadaun.co/shop/detail/dji/clmedia-2126/04.webp",
          "https://media.nadaun.co/shop/detail/dji/clmedia-2126/05.webp",
          "https://media.nadaun.co/shop/detail/dji/clmedia-2126/06.webp",
          "https://media.nadaun.co/shop/detail/dji/clmedia-2126/07.webp",
          "https://media.nadaun.co/shop/detail/dji/clmedia-2126/08.webp",
          "https://media.nadaun.co/shop/detail/dji/clmedia-2126/09.webp",
          "https://media.nadaun.co/shop/detail/dji/clmedia-2126/10.webp",
          "https://media.nadaun.co/shop/detail/dji/clmedia-2126/12.webp",
          "https://media.nadaun.co/shop/detail/dji/clmedia-2126/13.webp",
          "https://media.nadaun.co/shop/detail/dji/clmedia-2126/14.webp",
          "https://media.nadaun.co/shop/detail/dji/clmedia-2126/15.webp",
          "https://media.nadaun.co/shop/detail/dji/clmedia-2126/16.webp",
          "https://media.nadaun.co/shop/detail/dji/clmedia-2126/17.webp",
          "https://media.nadaun.co/shop/detail/dji/clmedia-2126/18.webp",
          "https://media.nadaun.co/shop/detail/dji/clmedia-2126/19.webp",
          "https://media.nadaun.co/shop/detail/dji/clmedia-2126/20.webp",
          "https://media.nadaun.co/shop/detail/dji/clmedia-2126/21.webp",
          "https://media.nadaun.co/shop/detail/dji/clmedia-2126/22.webp",
          "https://media.nadaun.co/shop/detail/dji/clmedia-2126/23.webp",
          "https://media.nadaun.co/shop/detail/dji/clmedia-2126/25.webp",
          "https://media.nadaun.co/shop/detail/dji/clmedia-2126/26.webp",
          "https://media.nadaun.co/shop/detail/dji/clmedia-2126/27.webp"
        ]
      }
    },
    "clmedia-2125": {
      "id": "clmedia-2125",
      "source": "clmedia",
      "source_id": "2125",
      "name": "디제이아이 오즈모 360 스탠다드콤보",
      "brand": "디제이아이",
      "brand_slug": "dji",
      "category": "Camera",
      "cat_path": [
        "Camera"
      ],
      "price": 616000,
      "source_url": "https://www.clmedia.co.kr/product/디제이아이-오즈모-360-스탠다드콤보/2125/category/136/display/1/",
      "images": {
        "thumb": "https://media.nadaun.co/shop/thumbnails/dji/clmedia-2125.webp",
        "main": [
          "https://media.nadaun.co/shop/images/dji/clmedia-2125/main_1.webp",
          "https://media.nadaun.co/shop/images/dji/clmedia-2125/main_2.webp",
          "https://media.nadaun.co/shop/images/dji/clmedia-2125/main_3.webp",
          "https://media.nadaun.co/shop/images/dji/clmedia-2125/main_4.webp",
          "https://media.nadaun.co/shop/images/dji/clmedia-2125/main_5.webp",
          "https://media.nadaun.co/shop/images/dji/clmedia-2125/main_6.webp",
          "https://media.nadaun.co/shop/images/dji/clmedia-2125/main_7.webp",
          "https://media.nadaun.co/shop/images/dji/clmedia-2125/main_8.webp"
        ],
        "detail": [
          "https://media.nadaun.co/shop/detail/dji/clmedia-2125/01.webp",
          "https://media.nadaun.co/shop/detail/dji/clmedia-2125/03.webp",
          "https://media.nadaun.co/shop/detail/dji/clmedia-2125/04.webp",
          "https://media.nadaun.co/shop/detail/dji/clmedia-2125/05.webp",
          "https://media.nadaun.co/shop/detail/dji/clmedia-2125/06.webp",
          "https://media.nadaun.co/shop/detail/dji/clmedia-2125/07.webp",
          "https://media.nadaun.co/shop/detail/dji/clmedia-2125/08.webp",
          "https://media.nadaun.co/shop/detail/dji/clmedia-2125/09.webp",
          "https://media.nadaun.co/shop/detail/dji/clmedia-2125/11.webp",
          "https://media.nadaun.co/shop/detail/dji/clmedia-2125/12.webp",
          "https://media.nadaun.co/shop/detail/dji/clmedia-2125/13.webp",
          "https://media.nadaun.co/shop/detail/dji/clmedia-2125/14.webp",
          "https://media.nadaun.co/shop/detail/dji/clmedia-2125/15.webp",
          "https://media.nadaun.co/shop/detail/dji/clmedia-2125/16.webp",
          "https://media.nadaun.co/shop/detail/dji/clmedia-2125/17.webp",
          "https://media.nadaun.co/shop/detail/dji/clmedia-2125/18.webp",
          "https://media.nadaun.co/shop/detail/dji/clmedia-2125/19.webp",
          "https://media.nadaun.co/shop/detail/dji/clmedia-2125/20.webp",
          "https://media.nadaun.co/shop/detail/dji/clmedia-2125/22.webp",
          "https://media.nadaun.co/shop/detail/dji/clmedia-2125/23.webp",
          "https://media.nadaun.co/shop/detail/dji/clmedia-2125/24.webp"
        ]
      }
    },
    "clmedia-1235": {
      "id": "clmedia-1235",
      "source": "clmedia",
      "source_id": "1235",
      "name": "디제이아이 오즈모 포켓3 크리에이터 콤보",
      "brand": "디제이아이",
      "brand_slug": "dji",
      "category": "Camera",
      "cat_path": [
        "Camera"
      ],
      "price": 934000,
      "source_url": "https://www.clmedia.co.kr/product/디제이아이-오즈모-포켓3-크리에이터-콤보/1235/category/136/display/1/",
      "images": {
        "thumb": "https://media.nadaun.co/shop/thumbnails/dji/clmedia-1235.webp",
        "main": [
          "https://media.nadaun.co/shop/images/dji/clmedia-1235/main_1.webp",
          "https://media.nadaun.co/shop/images/dji/clmedia-1235/main_2.webp",
          "https://media.nadaun.co/shop/images/dji/clmedia-1235/main_3.webp",
          "https://media.nadaun.co/shop/images/dji/clmedia-1235/main_4.webp",
          "https://media.nadaun.co/shop/images/dji/clmedia-1235/main_5.webp",
          "https://media.nadaun.co/shop/images/dji/clmedia-1235/main_6.webp",
          "https://media.nadaun.co/shop/images/dji/clmedia-1235/main_7.webp"
        ],
        "detail": [
          "https://media.nadaun.co/shop/detail/dji/clmedia-1235/01.webp",
          "https://media.nadaun.co/shop/detail/dji/clmedia-1235/03.webp",
          "https://media.nadaun.co/shop/detail/dji/clmedia-1235/04.webp",
          "https://media.nadaun.co/shop/detail/dji/clmedia-1235/05.webp",
          "https://media.nadaun.co/shop/detail/dji/clmedia-1235/06.webp",
          "https://media.nadaun.co/shop/detail/dji/clmedia-1235/07.webp",
          "https://media.nadaun.co/shop/detail/dji/clmedia-1235/08.webp",
          "https://media.nadaun.co/shop/detail/dji/clmedia-1235/10.webp",
          "https://media.nadaun.co/shop/detail/dji/clmedia-1235/11.webp",
          "https://media.nadaun.co/shop/detail/dji/clmedia-1235/12.webp",
          "https://media.nadaun.co/shop/detail/dji/clmedia-1235/13.webp",
          "https://media.nadaun.co/shop/detail/dji/clmedia-1235/14.webp",
          "https://media.nadaun.co/shop/detail/dji/clmedia-1235/15.webp",
          "https://media.nadaun.co/shop/detail/dji/clmedia-1235/16.webp",
          "https://media.nadaun.co/shop/detail/dji/clmedia-1235/17.webp",
          "https://media.nadaun.co/shop/detail/dji/clmedia-1235/18.webp",
          "https://media.nadaun.co/shop/detail/dji/clmedia-1235/20.webp",
          "https://media.nadaun.co/shop/detail/dji/clmedia-1235/21.webp",
          "https://media.nadaun.co/shop/detail/dji/clmedia-1235/22.webp"
        ]
      }
    },
    "clmedia-1234": {
      "id": "clmedia-1234",
      "source": "clmedia",
      "source_id": "1234",
      "name": "디제이아이 오즈모 포켓3 단품",
      "brand": "디제이아이",
      "brand_slug": "dji",
      "category": "Camera",
      "cat_path": [
        "Camera"
      ],
      "price": 726000,
      "source_url": "https://www.clmedia.co.kr/product/디제이아이-오즈모-포켓3-단품/1234/category/136/display/1/",
      "images": {
        "thumb": "https://media.nadaun.co/shop/thumbnails/dji/clmedia-1234.webp",
        "main": [
          "https://media.nadaun.co/shop/images/dji/clmedia-1234/main_1.webp",
          "https://media.nadaun.co/shop/images/dji/clmedia-1234/main_2.webp",
          "https://media.nadaun.co/shop/images/dji/clmedia-1234/main_3.webp",
          "https://media.nadaun.co/shop/images/dji/clmedia-1234/main_4.webp",
          "https://media.nadaun.co/shop/images/dji/clmedia-1234/main_5.webp",
          "https://media.nadaun.co/shop/images/dji/clmedia-1234/main_6.webp"
        ],
        "detail": [
          "https://media.nadaun.co/shop/detail/dji/clmedia-1234/01.webp",
          "https://media.nadaun.co/shop/detail/dji/clmedia-1234/03.webp",
          "https://media.nadaun.co/shop/detail/dji/clmedia-1234/04.webp",
          "https://media.nadaun.co/shop/detail/dji/clmedia-1234/05.webp",
          "https://media.nadaun.co/shop/detail/dji/clmedia-1234/06.webp",
          "https://media.nadaun.co/shop/detail/dji/clmedia-1234/07.webp",
          "https://media.nadaun.co/shop/detail/dji/clmedia-1234/09.webp",
          "https://media.nadaun.co/shop/detail/dji/clmedia-1234/10.webp",
          "https://media.nadaun.co/shop/detail/dji/clmedia-1234/11.webp",
          "https://media.nadaun.co/shop/detail/dji/clmedia-1234/12.webp",
          "https://media.nadaun.co/shop/detail/dji/clmedia-1234/13.webp",
          "https://media.nadaun.co/shop/detail/dji/clmedia-1234/14.webp",
          "https://media.nadaun.co/shop/detail/dji/clmedia-1234/15.webp",
          "https://media.nadaun.co/shop/detail/dji/clmedia-1234/16.webp",
          "https://media.nadaun.co/shop/detail/dji/clmedia-1234/17.webp",
          "https://media.nadaun.co/shop/detail/dji/clmedia-1234/19.webp",
          "https://media.nadaun.co/shop/detail/dji/clmedia-1234/20.webp",
          "https://media.nadaun.co/shop/detail/dji/clmedia-1234/21.webp"
        ]
      }
    },
    "clmedia-1233": {
      "id": "clmedia-1233",
      "source": "clmedia",
      "source_id": "1233",
      "name": "디제이아이 오즈모 액션5프로 어드벤쳐 콤보",
      "brand": "디제이아이",
      "brand_slug": "dji",
      "category": "Camera",
      "cat_path": [
        "Camera"
      ],
      "price": 639000,
      "source_url": "https://www.clmedia.co.kr/product/디제이아이-오즈모-액션5프로-어드벤쳐-콤보/1233/category/136/display/1/",
      "images": {
        "thumb": "https://media.nadaun.co/shop/thumbnails/dji/clmedia-1233.webp",
        "main": [
          "https://media.nadaun.co/shop/images/dji/clmedia-1233/main_1.webp",
          "https://media.nadaun.co/shop/images/dji/clmedia-1233/main_2.webp",
          "https://media.nadaun.co/shop/images/dji/clmedia-1233/main_3.webp",
          "https://media.nadaun.co/shop/images/dji/clmedia-1233/main_4.webp",
          "https://media.nadaun.co/shop/images/dji/clmedia-1233/main_5.webp",
          "https://media.nadaun.co/shop/images/dji/clmedia-1233/main_6.webp",
          "https://media.nadaun.co/shop/images/dji/clmedia-1233/main_7.webp",
          "https://media.nadaun.co/shop/images/dji/clmedia-1233/main_8.webp",
          "https://media.nadaun.co/shop/images/dji/clmedia-1233/main_9.webp"
        ],
        "detail": [
          "https://media.nadaun.co/shop/detail/dji/clmedia-1233/01.webp",
          "https://media.nadaun.co/shop/detail/dji/clmedia-1233/03.webp",
          "https://media.nadaun.co/shop/detail/dji/clmedia-1233/04.webp",
          "https://media.nadaun.co/shop/detail/dji/clmedia-1233/05.webp",
          "https://media.nadaun.co/shop/detail/dji/clmedia-1233/06.webp",
          "https://media.nadaun.co/shop/detail/dji/clmedia-1233/07.webp",
          "https://media.nadaun.co/shop/detail/dji/clmedia-1233/08.webp",
          "https://media.nadaun.co/shop/detail/dji/clmedia-1233/09.webp",
          "https://media.nadaun.co/shop/detail/dji/clmedia-1233/10.webp",
          "https://media.nadaun.co/shop/detail/dji/clmedia-1233/12.webp",
          "https://media.nadaun.co/shop/detail/dji/clmedia-1233/13.webp",
          "https://media.nadaun.co/shop/detail/dji/clmedia-1233/14.webp",
          "https://media.nadaun.co/shop/detail/dji/clmedia-1233/15.webp",
          "https://media.nadaun.co/shop/detail/dji/clmedia-1233/16.webp",
          "https://media.nadaun.co/shop/detail/dji/clmedia-1233/17.webp",
          "https://media.nadaun.co/shop/detail/dji/clmedia-1233/18.webp",
          "https://media.nadaun.co/shop/detail/dji/clmedia-1233/19.webp",
          "https://media.nadaun.co/shop/detail/dji/clmedia-1233/20.webp",
          "https://media.nadaun.co/shop/detail/dji/clmedia-1233/21.webp",
          "https://media.nadaun.co/shop/detail/dji/clmedia-1233/22.webp",
          "https://media.nadaun.co/shop/detail/dji/clmedia-1233/23.webp",
          "https://media.nadaun.co/shop/detail/dji/clmedia-1233/24.webp",
          "https://media.nadaun.co/shop/detail/dji/clmedia-1233/26.webp",
          "https://media.nadaun.co/shop/detail/dji/clmedia-1233/27.webp",
          "https://media.nadaun.co/shop/detail/dji/clmedia-1233/28.webp"
        ]
      }
    },
    "clmedia-2228": {
      "id": "clmedia-2228",
      "source": "clmedia",
      "source_id": "2228",
      "name": "디제이아이 MIC3 (2TX + 1RX)",
      "brand": "디제이아이",
      "brand_slug": "dji",
      "category": "Audio",
      "cat_path": [
        "Audio"
      ],
      "price": 469000,
      "source_url": "https://www.clmedia.co.kr/product/디제이아이-mic3-2tx-1rx/2228/category/254/display/1/",
      "images": {
        "thumb": "https://media.nadaun.co/shop/thumbnails/dji/clmedia-2228.webp",
        "main": [
          "https://media.nadaun.co/shop/images/dji/clmedia-2228/main_1.webp",
          "https://media.nadaun.co/shop/images/dji/clmedia-2228/main_2.webp",
          "https://media.nadaun.co/shop/images/dji/clmedia-2228/main_3.webp",
          "https://media.nadaun.co/shop/images/dji/clmedia-2228/main_4.webp",
          "https://media.nadaun.co/shop/images/dji/clmedia-2228/main_5.webp",
          "https://media.nadaun.co/shop/images/dji/clmedia-2228/main_6.webp",
          "https://media.nadaun.co/shop/images/dji/clmedia-2228/main_7.webp",
          "https://media.nadaun.co/shop/images/dji/clmedia-2228/main_8.webp"
        ],
        "detail": [
          "https://media.nadaun.co/shop/detail/dji/clmedia-2228/01.webp",
          "https://media.nadaun.co/shop/detail/dji/clmedia-2228/03.webp",
          "https://media.nadaun.co/shop/detail/dji/clmedia-2228/04.webp",
          "https://media.nadaun.co/shop/detail/dji/clmedia-2228/05.webp",
          "https://media.nadaun.co/shop/detail/dji/clmedia-2228/06.webp",
          "https://media.nadaun.co/shop/detail/dji/clmedia-2228/07.webp",
          "https://media.nadaun.co/shop/detail/dji/clmedia-2228/08.webp",
          "https://media.nadaun.co/shop/detail/dji/clmedia-2228/09.webp",
          "https://media.nadaun.co/shop/detail/dji/clmedia-2228/11.webp",
          "https://media.nadaun.co/shop/detail/dji/clmedia-2228/12.webp",
          "https://media.nadaun.co/shop/detail/dji/clmedia-2228/13.webp",
          "https://media.nadaun.co/shop/detail/dji/clmedia-2228/14.webp",
          "https://media.nadaun.co/shop/detail/dji/clmedia-2228/15.webp",
          "https://media.nadaun.co/shop/detail/dji/clmedia-2228/16.webp",
          "https://media.nadaun.co/shop/detail/dji/clmedia-2228/17.webp",
          "https://media.nadaun.co/shop/detail/dji/clmedia-2228/18.webp",
          "https://media.nadaun.co/shop/detail/dji/clmedia-2228/19.webp",
          "https://media.nadaun.co/shop/detail/dji/clmedia-2228/20.webp",
          "https://media.nadaun.co/shop/detail/dji/clmedia-2228/21.webp",
          "https://media.nadaun.co/shop/detail/dji/clmedia-2228/23.webp",
          "https://media.nadaun.co/shop/detail/dji/clmedia-2228/24.webp",
          "https://media.nadaun.co/shop/detail/dji/clmedia-2228/25.webp"
        ]
      }
    },
    "clmedia-228": {
      "id": "clmedia-228",
      "source": "clmedia",
      "source_id": "228",
      "name": "디제이아이 MIC MINI (2TX + 1RX) 마이크 미니",
      "brand": "디제이아이",
      "brand_slug": "dji",
      "category": "Audio",
      "cat_path": [
        "Audio"
      ],
      "price": 153000,
      "source_url": "https://www.clmedia.co.kr/product/디제이아이-mic-mini-2tx-1rx-마이크-미니/228/category/254/display/1/",
      "images": {
        "thumb": "https://media.nadaun.co/shop/thumbnails/dji/clmedia-228.webp",
        "main": [
          "https://media.nadaun.co/shop/images/dji/clmedia-228/main_1.webp",
          "https://media.nadaun.co/shop/images/dji/clmedia-228/main_2.webp",
          "https://media.nadaun.co/shop/images/dji/clmedia-228/main_3.webp",
          "https://media.nadaun.co/shop/images/dji/clmedia-228/main_4.webp",
          "https://media.nadaun.co/shop/images/dji/clmedia-228/main_5.webp",
          "https://media.nadaun.co/shop/images/dji/clmedia-228/main_6.webp",
          "https://media.nadaun.co/shop/images/dji/clmedia-228/main_7.webp",
          "https://media.nadaun.co/shop/images/dji/clmedia-228/main_8.webp"
        ],
        "detail": [
          "https://media.nadaun.co/shop/detail/dji/clmedia-228/01.webp",
          "https://media.nadaun.co/shop/detail/dji/clmedia-228/03.webp",
          "https://media.nadaun.co/shop/detail/dji/clmedia-228/04.webp",
          "https://media.nadaun.co/shop/detail/dji/clmedia-228/05.webp",
          "https://media.nadaun.co/shop/detail/dji/clmedia-228/06.webp",
          "https://media.nadaun.co/shop/detail/dji/clmedia-228/07.webp",
          "https://media.nadaun.co/shop/detail/dji/clmedia-228/08.webp",
          "https://media.nadaun.co/shop/detail/dji/clmedia-228/09.webp",
          "https://media.nadaun.co/shop/detail/dji/clmedia-228/11.webp",
          "https://media.nadaun.co/shop/detail/dji/clmedia-228/12.webp",
          "https://media.nadaun.co/shop/detail/dji/clmedia-228/13.webp",
          "https://media.nadaun.co/shop/detail/dji/clmedia-228/14.webp",
          "https://media.nadaun.co/shop/detail/dji/clmedia-228/15.webp",
          "https://media.nadaun.co/shop/detail/dji/clmedia-228/16.webp",
          "https://media.nadaun.co/shop/detail/dji/clmedia-228/17.webp",
          "https://media.nadaun.co/shop/detail/dji/clmedia-228/18.webp",
          "https://media.nadaun.co/shop/detail/dji/clmedia-228/19.webp",
          "https://media.nadaun.co/shop/detail/dji/clmedia-228/20.webp",
          "https://media.nadaun.co/shop/detail/dji/clmedia-228/21.webp",
          "https://media.nadaun.co/shop/detail/dji/clmedia-228/22.webp",
          "https://media.nadaun.co/shop/detail/dji/clmedia-228/23.webp",
          "https://media.nadaun.co/shop/detail/dji/clmedia-228/24.webp",
          "https://media.nadaun.co/shop/detail/dji/clmedia-228/26.webp",
          "https://media.nadaun.co/shop/detail/dji/clmedia-228/27.webp",
          "https://media.nadaun.co/shop/detail/dji/clmedia-228/28.webp"
        ]
      }
    },
    "clmedia-207": {
      "id": "clmedia-207",
      "source": "clmedia",
      "source_id": "207",
      "name": "디제이아이 Mic 2 (2 TX + 1 RX + 충전 케이스) 무선마이크 2채널 충전 케이스 포함",
      "brand": "디제이아이",
      "brand_slug": "dji",
      "category": "Audio",
      "cat_path": [
        "Audio"
      ],
      "price": 333000,
      "source_url": "https://www.clmedia.co.kr/product/디제이아이-mic-2-2-tx-1-rx-충전-케이스-무선마이크-2채널-충전-케이스-포함/207/category/254/display/1/",
      "images": {
        "thumb": "https://media.nadaun.co/shop/thumbnails/dji/clmedia-207.webp",
        "main": [
          "https://media.nadaun.co/shop/images/dji/clmedia-207/main_1.webp",
          "https://media.nadaun.co/shop/images/dji/clmedia-207/main_2.webp",
          "https://media.nadaun.co/shop/images/dji/clmedia-207/main_3.webp",
          "https://media.nadaun.co/shop/images/dji/clmedia-207/main_4.webp",
          "https://media.nadaun.co/shop/images/dji/clmedia-207/main_5.webp",
          "https://media.nadaun.co/shop/images/dji/clmedia-207/main_6.webp",
          "https://media.nadaun.co/shop/images/dji/clmedia-207/main_7.webp",
          "https://media.nadaun.co/shop/images/dji/clmedia-207/main_8.webp"
        ],
        "detail": [
          "https://media.nadaun.co/shop/detail/dji/clmedia-207/01.webp",
          "https://media.nadaun.co/shop/detail/dji/clmedia-207/03.webp",
          "https://media.nadaun.co/shop/detail/dji/clmedia-207/04.webp",
          "https://media.nadaun.co/shop/detail/dji/clmedia-207/05.webp",
          "https://media.nadaun.co/shop/detail/dji/clmedia-207/06.webp",
          "https://media.nadaun.co/shop/detail/dji/clmedia-207/07.webp",
          "https://media.nadaun.co/shop/detail/dji/clmedia-207/08.webp",
          "https://media.nadaun.co/shop/detail/dji/clmedia-207/09.webp",
          "https://media.nadaun.co/shop/detail/dji/clmedia-207/11.webp",
          "https://media.nadaun.co/shop/detail/dji/clmedia-207/12.webp",
          "https://media.nadaun.co/shop/detail/dji/clmedia-207/13.webp",
          "https://media.nadaun.co/shop/detail/dji/clmedia-207/14.webp",
          "https://media.nadaun.co/shop/detail/dji/clmedia-207/16.webp",
          "https://media.nadaun.co/shop/detail/dji/clmedia-207/17.webp",
          "https://media.nadaun.co/shop/detail/dji/clmedia-207/18.webp"
        ]
      }
    }
  }
}